<?xml version="1.0" encoding="utf-8" standalone="yes" ?>
<T3locallang>
	<meta type="array">
		<type>module</type>
		<description>Language labels for the address management extension</description>
	</meta>
	<data type="array">
		<languageKey index="default" type="array">
			<label index="phone">Telephone:</label>
			<label index="fax">Fax number:</label>
			<label index="www">Website:</label>
			<label index="email">Email:</label>
			<label index="f">Mrs.</label>
			<label index="m">Mr.</label>
			<label index="back_to_list">Back to list</label>
			<label index="next">next</label>
			<label index="download_vcard">Download as vCard</label>
			<label index="download_vcards">Download whole list as vCards</label>
		</languageKey>
		<languageKey index="de" type="array">
			<label index="phone">Telefon:</label>
			<label index="fax">Fax:</label>
			<label index="back_to_list">Zurück zur Übersicht</label>
			<label index="next">next</label>
			<label index="download_vcard">vCard-Download</label>
			<label index="download_vcards">Alle Adressen als vCard herunterladen</label>
		</languageKey>
	</data>
</T3locallang>